macrometa_target_bigquery/__init__.py
macrometa_target_bigquery/db_sync.py
macrometa_target_bigquery/exceptions.py
macrometa_target_bigquery/flattening.py
macrometa_target_bigquery/sql_utils.py
macrometa_target_bigquery/stream_ref_helper.py
macrometa_target_bigquery/stream_utils.py
macrometa_target_bigquery-1.0.0.dist-info/LICENSE
macrometa_target_bigquery-1.0.0.dist-info/METADATA
macrometa_target_bigquery-1.0.0.dist-info/WHEEL
macrometa_target_bigquery-1.0.0.dist-info/entry_points.txt
macrometa_target_bigquery-1.0.0.dist-info/top_level.txt
macrometa_target_bigquery-1.0.0.dist-info/RECORD
