Metadata-Version: 2.1
Name: macrometa-target-bigquery
Version: 1.0.0
Summary: Macrometa target bigquery connector for loading data to BigQuery
Home-page: https://github.com/Macrometacorp/macrometa-target-bigquery
Author: Macrometa
Classifier: License :: OSI Approved :: Apache Software License
Classifier: Programming Language :: Python :: 3 :: Only
License-File: LICENSE
Requires-Dist: pipelinewise-singer-python (==1.2.0)
Requires-Dist: google-cloud-bigquery (<3.1.0,>=2.20.0)
Requires-Dist: fastavro (<1.4.11,>=0.22.8)
Requires-Dist: c8connector (>=0.0.29)
Requires-Dist: prometheus-client (==0.16.0)
Provides-Extra: test
Requires-Dist: pytest (==7.0.1) ; extra == 'test'
Requires-Dist: pylint (==2.13.4) ; extra == 'test'
Requires-Dist: pytest-cov (==3.0.0) ; extra == 'test'
